CHANGELOG.md
semverize/__init__.py
semverize/_convert.py
semverize/cli.py
semverize/py.typed
semverize-0.1.0.dist-info/entry_points.txt
semverize-0.1.0.dist-info/LICENSE
semverize-0.1.0.dist-info/WHEEL
semverize-0.1.0.dist-info/METADATA
semverize-0.1.0.dist-info/RECORD
