Metadata-Version: 2.1
Name: semverize
Version: 0.1.0
Summary: Coerce PEP 440 to SemVer, when possible
Home-page: https://github.com/metabolize/semverize
License: Apache-2.0
Author: Paul Melnikow
Author-email: github@paulmelnikow.com
Requires-Python: >=3.9,<4
Classifier: Development Status :: 3 - Alpha
Classifier: Intended Audience :: Developers
Classifier: License :: OSI Approved :: Apache Software License
Classifier: Operating System :: OS Independent
Classifier: Programming Language :: Python :: 3
Classifier: Programming Language :: Python :: 3.9
Classifier: Programming Language :: Python :: 3.10
Classifier: Programming Language :: Python :: 3.11
Classifier: Topic :: Utilities
Classifier: Typing :: Typed
Provides-Extra: cli
Requires-Dist: click (>=8,<9); extra == "cli"
Requires-Dist: packaging (>=23.0)
Requires-Dist: semver (>=3,<4)
Project-URL: Repository, https://github.com/metabolize/semverize
